aiorwlock/__init__.py
aiorwlock/py.typed
rijenkii_aiorwlock-1.3.0.dist-info/LICENSE
rijenkii_aiorwlock-1.3.0.dist-info/METADATA
rijenkii_aiorwlock-1.3.0.dist-info/WHEEL
rijenkii_aiorwlock-1.3.0.dist-info/top_level.txt
rijenkii_aiorwlock-1.3.0.dist-info/zip-safe
rijenkii_aiorwlock-1.3.0.dist-info/RECORD
