Metadata-Version: 2.1
Name: rijenkii-aiorwlock
Version: 1.3.0
Summary: Read write lock for asyncio.
Home-page: https://github.com/rijenkii/aiorwlock
Download-URL: https://pypi.python.org/pypi/aiorwlock
Author: Nikolay Novik
Author-email: nickolainovik@gmail.com
License: Apache 2
Project-URL: Website, https://github.com/rijenkii/aiorwlock
Project-URL: Issues, https://github.com/rijenkii/aiorwlock/issues
Keywords: aiorwlock,lock,asyncio
Platform: POSIX
Classifier: License :: OSI Approved :: Apache Software License
Classifier: Intended Audience :: Developers
Classifier: Programming Language :: Python :: 3
Classifier: Programming Language :: Python :: 3.7
Classifier: Programming Language :: Python :: 3.8
Classifier: Programming Language :: Python :: 3.9
Classifier: Programming Language :: Python :: 3.10
Classifier: Operating System :: OS Independent
Classifier: Development Status :: 4 - Beta
Classifier: Framework :: AsyncIO
Requires-Python: >=3.7.0
License-File: LICENSE
